<?xml version="1.0" encoding="utf-8"?>
<trait alwaysVisible="1"
       category="Buff"
       icon="Weapons/Deathshriek">
    <onCombatOpponentModifiers>
        <modifier>
            <conditions>
                <encounter>
                    <self>
                        <destroyed/>
                    </self>
                    <opponent>
                        <attacking/>
                    </opponent>
                </encounter>
            </conditions>
            <effects>
                <morale add="-100"/>
                <addTrait name="VehicleHeavilyDamaged"
                          duration="2"/>
                <addTrait name="Desperation"
                          duration="2"/>
                <weaponDamage weapon="DeathPact"/>
            </effects>
        </modifier>
    </onCombatOpponentModifiers>
</trait>
